README.md
setup.py
Flask_FrameMVC/App.py
Flask_FrameMVC/__init__.py
Flask_FrameMVC/conventions.py
Flask_FrameMVC.egg-info/PKG-INFO
Flask_FrameMVC.egg-info/SOURCES.txt
Flask_FrameMVC.egg-info/dependency_links.txt
Flask_FrameMVC.egg-info/requires.txt
Flask_FrameMVC.egg-info/top_level.txt
Flask_FrameMVC/AppFactory/__init__.py
Flask_FrameMVC/AppFactory/basic.py
Flask_FrameMVC/AppFactory/http.py
Flask_FrameMVC/AppFactory/websocket.py
Flask_FrameMVC/ConfigContainer/__init__.py
Flask_FrameMVC/Scanner/__init__.py
Flask_FrameMVC/Scanner/load.py
Flask_FrameMVC/Scanner/scan.py
Flask_FrameMVC/core/__init__.py
Flask_FrameMVC/core/Basics/__init__.py
Flask_FrameMVC/core/Basics/config.py
Flask_FrameMVC/core/Basics/controller.py
Flask_FrameMVC/core/Basics/interaction.py
Flask_FrameMVC/core/Basics/servlet.py
Flask_FrameMVC/core/Exception/Exceptions.py
Flask_FrameMVC/core/Exception/__init__.py
Flask_FrameMVC/core/Exception/handler.py
Flask_FrameMVC/core/servlet/BootMiddleWare.py
Flask_FrameMVC/core/servlet/__init__.py
Flask_FrameMVC/default/__init__.py
Flask_FrameMVC/default/config/ServletConfig.py
Flask_FrameMVC/default/config/SwaggerConfig.py
Flask_FrameMVC/default/config/__init__.py
Flask_FrameMVC/default/controller/PluginHttpController.py
Flask_FrameMVC/default/controller/TestHttpControllerFactory.py
Flask_FrameMVC/default/controller/__init__.py
Flask_FrameMVC/default/dao/PluginDao.py
Flask_FrameMVC/default/dao/__init__.py
Flask_FrameMVC/default/entity/__init__.py
Flask_FrameMVC/default/entity/do/Plugin.py
Flask_FrameMVC/default/entity/do/__init__.py
Flask_FrameMVC/default/router/PluginHttpRouter.py
Flask_FrameMVC/default/router/TestHttpRouter.py
Flask_FrameMVC/default/router/__init__.py
Flask_FrameMVC/default/service/PluginServiceInterface.py
Flask_FrameMVC/default/service/__init__.py
Flask_FrameMVC/default/service/Impl/PluginServiceImpl.py
Flask_FrameMVC/default/service/Impl/__init__.py
Flask_FrameMVC/side/BasicSide.py
Flask_FrameMVC/side/PluginSide.py
Flask_FrameMVC/side/TestSide.py
Flask_FrameMVC/side/__init__.py